Workbook
Name Сценарий_индекс: Допущения!$C$4
Name Выручка_база: Допущения!$B$7
Name Темп_роста: Допущения!$B$11
Name Маржа_2026: Допущения!$B$13
Name Маржа_прирост: Допущения!$B$14
Name Опер_расходы_доля: Допущения!$B$15
Name Налог: Допущения!$B$16
Name Капзатраты_2026: Допущения!$B$18
Name Капзатраты_спад: Допущения!$B$19
Name Срок_аморт: Допущения!$B$20
Name ОК_доля: Допущения!$B$21
Name WACC: Допущения!$B$27

Sheet Допущения
A1: Допущения модели
A2: Синим — вводимые значения. Меняйте только их.
A4: Сценарий | B4: База | C4: =MATCH(B4,{"Пессимистичный";"База";"Оптимистичный"},0) -> 2 | D4: ← индекс сценария
A6: Драйверы роста
A7: Базовая выручка 2025, млн ₽ | B7: 4558
A8: Темп роста — пессимистичный | B8: 0.08
A9: Темп роста — базовый | B9: 0.165
A10: Темп роста — оптимистичный | B10: 0.24
A11: Активный темп роста | B11: =CHOOSE($C$4,$B$8,$B$9,$B$10) -> 0.165 | C11: Выбирается сценарием
A12: Экономика
A13: Валовая маржа 2026 | B13: 0.412
A14: Годовое улучшение маржи, п.п. | B14: 0.006
A15: Опер. расходы, % выручки | B15: 0.192
A16: Ставка налога на прибыль | B16: 0.2
A17: Капитал
A18: Капзатраты 2026, млн ₽ | B18: 980
A19: Снижение капзатрат в год | B19: 0.06
A20: Срок амортизации, лет | B20: 8
A21: Оборотный капитал, % выручки | B21: 0.084
A22: Стоимость капитала
A23: Безрисковая ставка | B23: 0.082
A24: Премия за риск | B24: 0.055
A25: Стоимость долга | B25: 0.115
A26: Доля долга в капитале | B26: 0.35
A27: WACC | B27: =(1-$B$26)*($B$23+$B$24)+$B$26*$B$25*(1-$B$16) -> 0.12125 | C27: С учётом налогового щита

Sheet Прогноз P&L
A1: Прогноз отчёта о прибылях и убытках
A2: млн ₽, если не указано иное
A4: Показатель | B4: 2026 | C4: 2027 | D4: 2028 | E4: 2029 | F4: 2030 | G4: CAGR
A5: Выручка | B5: =Выручка_база*(1+Темп_роста) -> 5310.07 | C5: =B5*(1+Темп_роста) -> 6186.2315 | D5: =C5*(1+Темп_роста) -> 7206.9598 | E5: =D5*(1+Темп_роста) -> 8396.1081 | F5: =E5*(1+Темп_роста) -> 9781.466 | G5: =IFERROR((F5/B5)^(1/4)-1,"") -> 0.165
A6: Валовая маржа, % | B6: =Маржа_2026+Маржа_прирост*0 -> 0.412 | C6: =Маржа_2026+Маржа_прирост*1 -> 0.418 | D6: =Маржа_2026+Маржа_прирост*2 -> 0.424 | E6: =Маржа_2026+Маржа_прирост*3 -> 0.43 | F6: =Маржа_2026+Маржа_прирост*4 -> 0.436
A7: Валовая прибыль | B7: =B5*B6 -> 2187.7488 | C7: =C5*C6 -> 2585.8448 | D7: =D5*D6 -> 3055.7509 | E7: =E5*E6 -> 3610.3265 | F7: =F5*F6 -> 4264.7192 | G7: =IFERROR((F7/B7)^(1/4)-1,"") -> 0.18160751
A8: Операционные расходы | B8: =-B5*Опер_расходы_доля -> -1019.5334 | C8: =-C5*Опер_расходы_доля -> -1187.7565 | D8: =-D5*Опер_расходы_доля -> -1383.7363 | E8: =-E5*Опер_расходы_доля -> -1612.0528 | F8: =-F5*Опер_расходы_доля -> -1878.0415 | G8: =IFERROR((F8/B8)^(1/4)-1,"") -> 0.165
A9: EBITDA | B9: =B7+B8 -> 1168.2154 | C9: =C7+C8 -> 1398.0883 | D9: =D7+D8 -> 1672.0147 | E9: =E7+E8 -> 1998.2737 | F9: =F7+F8 -> 2386.6777 | G9: =IFERROR((F9/B9)^(1/4)-1,"") -> 0.19554991
A10: Рентабельность EBITDA | B10: =B9/B5 -> 0.22 | C10: =C9/C5 -> 0.226 | D10: =D9/D5 -> 0.232 | E10: =E9/E5 -> 0.238 | F10: =F9/F5 -> 0.244
A11: Амортизация | B11: =-Капзатраты_2026/Срок_аморт*1 -> -122.5 | C11: =-Капзатраты_2026/Срок_аморт*2 -> -245 | D11: =-Капзатраты_2026/Срок_аморт*3 -> -367.5 | E11: =-Капзатраты_2026/Срок_аморт*4 -> -490 | F11: =-Капзатраты_2026/Срок_аморт*5 -> -612.5 | G11: =IFERROR((F11/B11)^(1/4)-1,"") -> 0.49534878
A12: EBIT | B12: =B9+B11 -> 1045.7154 | C12: =C9+C11 -> 1153.0883 | D12: =D9+D11 -> 1304.5147 | E12: =E9+E11 -> 1508.2737 | F12: =F9+F11 -> 1774.1777 | G12: =IFERROR((F12/B12)^(1/4)-1,"") -> 0.14128971
A13: Налог на прибыль | B13: =-MAX(0,B12)*Налог -> -209.14308 | C13: =-MAX(0,C12)*Налог -> -230.61767 | D13: =-MAX(0,D12)*Налог -> -260.90293 | E13: =-MAX(0,E12)*Налог -> -301.65475 | F13: =-MAX(0,F12)*Налог -> -354.83554 | G13: =IFERROR((F13/B13)^(1/4)-1,"") -> 0.14128971
A14: Чистая прибыль | B14: =B12+B13 -> 836.57232 | C14: =C12+C13 -> 922.47066 | D14: =D12+D13 -> 1043.6117 | E14: =E12+E13 -> 1206.619 | F14: =F12+F13 -> 1419.3422 | G14: =IFERROR((F14/B14)^(1/4)-1,"") -> 0.14128971
A16: Проверка: EBITDA = Валовая прибыль + Опер. расходы | B16: =IF(SUMPRODUCT(--(ABS(B9:F9-(B7:F7+B8:F8))>0.001))=0,"OK","ОШИБКА") -> OK

Sheet DCF
A1: Дисконтированный денежный поток
A2: Оценка на 16 августа 2026 года
A4: Показатель | B4: 2026 | C4: 2027 | D4: 2028 | E4: 2029 | F4: 2030
A5: EBITDA | B5: ='Прогноз P&L'!B9 -> 1168.2154 | C5: ='Прогноз P&L'!C9 -> 1398.0883 | D5: ='Прогноз P&L'!D9 -> 1672.0147 | E5: ='Прогноз P&L'!E9 -> 1998.2737 | F5: ='Прогноз P&L'!F9 -> 2386.6777
A6: Налог (кассовый) | B6: ='Прогноз P&L'!B13 -> -209.14308 | C6: ='Прогноз P&L'!C13 -> -230.61767 | D6: ='Прогноз P&L'!D13 -> -260.90293 | E6: ='Прогноз P&L'!E13 -> -301.65475 | F6: ='Прогноз P&L'!F13 -> -354.83554
A7: Капитальные затраты | B7: =-Капзатраты_2026*(1-Капзатраты_спад)^0 -> -980 | C7: =-Капзатраты_2026*(1-Капзатраты_спад)^1 -> -921.2 | D7: =-Капзатраты_2026*(1-Капзатраты_спад)^2 -> -865.928 | E7: =-Капзатраты_2026*(1-Капзатраты_спад)^3 -> -813.97232 | F7: =-Капзатраты_2026*(1-Капзатраты_спад)^4 -> -765.13398
A8: Изменение оборотного капитала | B8: =-('Прогноз P&L'!B5-Выручка_база)*ОК_доля -> -63.17388 | C8: =-('Прогноз P&L'!C5-'Прогноз P&L'!B5)*ОК_доля -> -73.59757 | D8: =-('Прогноз P&L'!D5-'Прогноз P&L'!C5)*ОК_доля -> -85.741169 | E8: =-('Прогноз P&L'!E5-'Прогноз P&L'!D5)*ОК_доля -> -99.888462 | F8: =-('Прогноз P&L'!F5-'Прогноз P&L'!E5)*ОК_доля -> -116.37006
A9: Свободный денежный поток | B9: =SUM(B5:B8) -> -84.10156 | C9: =SUM(C5:C8) -> 172.67309 | D9: =SUM(D5:D8) -> 459.44256 | E9: =SUM(E5:E8) -> 782.7582 | F9: =SUM(F5:F8) -> 1150.3381
A10: Коэффициент дисконтирования | B10: =1/(1+WACC)^1 -> 0.89186176 | C10: =1/(1+WACC)^2 -> 0.7954174 | D10: =1/(1+WACC)^3 -> 0.70940236 | E10: =1/(1+WACC)^4 -> 0.63268884 | F10: =1/(1+WACC)^5 -> 0.56427099
A11: Дисконтированный FCF | B11: =B9*B10 -> -75.006965 | C11: =C9*C10 -> 137.34718 | D11: =D9*D10 -> 325.92964 | E11: =E9*E10 -> 495.24238 | F11: =F9*F10 -> 649.10242
A13: Поток для IRR (t₀ … t₅) | B13: =B16 -> -1450 | C13: =B9 -> -84.10156 | D13: =C9 -> 172.67309 | E13: =D9 -> 459.44256 | F13: =E9 -> 782.7582 | G13: =F9 -> 1150.3381
A16: Первоначальные вложения (2025) | B16: -1450
A17: Сумма дисконтированных FCF | B17: =SUM(B11:F11) -> 1532.6147
A18: Терминальная стоимость (g = 3 %) | B18: =F9*(1+0.03)/(WACC-0.03)*F10 -> 7326.8547
A19: NPV программы (без терминальной стоимости) | B19: =B16+B17 -> 82.614661
A20: Стоимость бизнеса (EV) | B20: =B17+B18 -> 8859.4694
A21: Чистый долг | B21: 2380
A22: Стоимость капитала | B22: =B20-B21 -> 6479.4694
A23: IRR проекта | B23: =IRR(B13:G13) -> 0.1362307

Sheet Чувствительность
A1: Матрица чувствительности NPV
A2: Строки — WACC, столбцы — темп роста выручки. млн ₽
A4: WACC \ Рост | B4: 0.08 | C4: 0.12 | D4: 0.165 | E4: 0.2 | F4: 0.24
A5: 0.11 | B5: =ROUND(Выручка_база*(1+B$4)^5*0.22/(1+$A5)^5*5-SUM(DCF!$B$7:$F$7)*-1,0) -> 26 | C5: =ROUND(Выручка_база*(1+C$4)^5*0.22/(1+$A5)^5*5-SUM(DCF!$B$7:$F$7)*-1,0) -> 898 | D5: =ROUND(Выручка_база*(1+D$4)^5*0.22/(1+$A5)^5*5-SUM(DCF!$B$7:$F$7)*-1,0) -> 2039 | E5: =ROUND(Выручка_база*(1+E$4)^5*0.22/(1+$A5)^5*5-SUM(DCF!$B$7:$F$7)*-1,0) -> 3058 | F5: =ROUND(Выручка_база*(1+F$4)^5*0.22/(1+$A5)^5*5-SUM(DCF!$B$7:$F$7)*-1,0) -> 4377
A6: 0.125 | B6: =ROUND(Выручка_база*(1+B$4)^5*0.22/(1+$A6)^5*5-SUM(DCF!$B$7:$F$7)*-1,0) -> -258 | C6: =ROUND(Выручка_база*(1+C$4)^5*0.22/(1+$A6)^5*5-SUM(DCF!$B$7:$F$7)*-1,0) -> 557 | D6: =ROUND(Выручка_база*(1+D$4)^5*0.22/(1+$A6)^5*5-SUM(DCF!$B$7:$F$7)*-1,0) -> 1625 | E6: =ROUND(Выручка_база*(1+E$4)^5*0.22/(1+$A6)^5*5-SUM(DCF!$B$7:$F$7)*-1,0) -> 2577 | F6: =ROUND(Выручка_база*(1+F$4)^5*0.22/(1+$A6)^5*5-SUM(DCF!$B$7:$F$7)*-1,0) -> 3810
A7: 0.14 | B7: =ROUND(Выручка_база*(1+B$4)^5*0.22/(1+$A7)^5*5-SUM(DCF!$B$7:$F$7)*-1,0) -> -520 | C7: =ROUND(Выручка_база*(1+C$4)^5*0.22/(1+$A7)^5*5-SUM(DCF!$B$7:$F$7)*-1,0) -> 243 | D7: =ROUND(Выручка_база*(1+D$4)^5*0.22/(1+$A7)^5*5-SUM(DCF!$B$7:$F$7)*-1,0) -> 1242 | E7: =ROUND(Выручка_база*(1+E$4)^5*0.22/(1+$A7)^5*5-SUM(DCF!$B$7:$F$7)*-1,0) -> 2133 | F7: =ROUND(Выручка_база*(1+F$4)^5*0.22/(1+$A7)^5*5-SUM(DCF!$B$7:$F$7)*-1,0) -> 3288
A8: 0.155 | B8: =ROUND(Выручка_база*(1+B$4)^5*0.22/(1+$A8)^5*5-SUM(DCF!$B$7:$F$7)*-1,0) -> -762 | C8: =ROUND(Выручка_база*(1+C$4)^5*0.22/(1+$A8)^5*5-SUM(DCF!$B$7:$F$7)*-1,0) -> -47 | D8: =ROUND(Выручка_база*(1+D$4)^5*0.22/(1+$A8)^5*5-SUM(DCF!$B$7:$F$7)*-1,0) -> 888 | E8: =ROUND(Выручка_база*(1+E$4)^5*0.22/(1+$A8)^5*5-SUM(DCF!$B$7:$F$7)*-1,0) -> 1723 | F8: =ROUND(Выручка_база*(1+F$4)^5*0.22/(1+$A8)^5*5-SUM(DCF!$B$7:$F$7)*-1,0) -> 2805
A9: 0.17 | B9: =ROUND(Выручка_база*(1+B$4)^5*0.22/(1+$A9)^5*5-SUM(DCF!$B$7:$F$7)*-1,0) -> -986 | C9: =ROUND(Выручка_база*(1+C$4)^5*0.22/(1+$A9)^5*5-SUM(DCF!$B$7:$F$7)*-1,0) -> -316 | D9: =ROUND(Выручка_база*(1+D$4)^5*0.22/(1+$A9)^5*5-SUM(DCF!$B$7:$F$7)*-1,0) -> 561 | E9: =ROUND(Выручка_база*(1+E$4)^5*0.22/(1+$A9)^5*5-SUM(DCF!$B$7:$F$7)*-1,0) -> 1344 | F9: =ROUND(Выручка_база*(1+F$4)^5*0.22/(1+$A9)^5*5-SUM(DCF!$B$7:$F$7)*-1,0) -> 2358
A12: Зелёные ячейки — сочетания, при которых программа создаёт стоимость.

Sheet Реестр объектов
A1: Реестр объектов модернизации
A2: Сгруппировано по регионам
A4: Регион | B4: Площадка | C4: Тип | D4: Мощность, МВт·ч | E4: Капзатраты, млн ₽ | F4: Ввод | G4: Готовность
A5: Северо-Запад | B5: Псков-1 | C5: Контейнерный | D5: 24 | E5: 186 | F5: 2026-Q2 | G5: 0.92
A6: Северо-Запад | B6: Псков-2 | C6: Контейнерный | D6: 18 | E6: 141 | F6: 2026-Q4 | G6: 0.64
A7: Северо-Запад | B7: Великие Луки | C7: Модульный | D7: 12 | E7: 98 | F7: 2027-Q1 | G7: 0.31
A8: Центр | B8: Тула-Восток | C8: Контейнерный | D8: 32 | E8: 244 | F8: 2026-Q3 | G8: 0.78
A9: Центр | B9: Калуга-Юг | C9: Контейнерный | D9: 28 | E9: 213 | F9: 2027-Q2 | G9: 0.22
A10: Центр | B10: Рязань | C10: Модульный | D10: 14 | E10: 112 | F10: 2027-Q3 | G10: 0.08
A11: Урал | B11: Екатеринбург-Север | C11: Контейнерный | D11: 40 | E11: 305 | F11: 2026-Q4 | G11: 0.55
A12: Урал | B12: Челябинск | C12: Контейнерный | D12: 36 | E12: 274 | F12: 2027-Q4 | G12: 0.14
A13: Сибирь | B13: Новосибирск | C13: Модульный | D13: 22 | E13: 178 | F13: 2028-Q1 | G13: 0.05
A14: Сибирь | B14: Кемерово | C14: Контейнерный | D14: 26 | E14: 199 | F14: 2028-Q2 | G14: 0
A15: Итого | D15: =SUBTOTAL(109,D5:D14) | E15: =SUBTOTAL(109,E5:E14) | G15: =SUBTOTAL(101,G5:G14)

Sheet Графики
A1: Графики
A2: Связаны с листами прогноза — обновляются при пересчёте
